{
  "changelogDate": "20221009153552",
  "clientRootFolder": "restaurantdb",
  "databaseType": "mongodb",
  "dto": "mapstruct",
  "fields": [
    {
      "fieldName": "name",
      "fieldType": "String"
    },
    {
      "fieldName": "phone",
      "fieldType": "String"
    },
    {
      "fieldName": "adress",
      "fieldType": "String"
    },
    {
      "fieldName": "photo",
      "fieldType": "byte[]",
      "fieldTypeBlobContent": "image"
    }
  ],
  "microserviceName": "restaurantdb",
  "name": "Restaurant",
  "pagination": "no",
  "readOnly": false,
  "relationships": [],
  "service": "serviceClass"
}
